jinja2_htmlmin/__init__.py
jinja2_htmlmin/py.typed
jinja2_htmlmin-1.0.1.dist-info/METADATA
jinja2_htmlmin-1.0.1.dist-info/WHEEL
jinja2_htmlmin-1.0.1.dist-info/licenses/LICENSE
jinja2_htmlmin-1.0.1.dist-info/RECORD
