Metadata-Version: 2.4
Name: jinja2-htmlmin
Version: 1.0.1
Summary: Automatic HTML minification for Jinja2 templates
Project-URL: Repository, https://github.com/Zaczero/jinja2-htmlmin
Project-URL: Issues, https://github.com/Zaczero/jinja2-htmlmin/issues
Author-email: Kamil Monicz <kamil@monicz.dev>
License-Expression: 0BSD
License-File: LICENSE
Keywords: fastapi,html,htmlmin,jinja,jinja2,minification,minify,optimization,performance,response,starlette,template,web
Classifier: Development Status :: 5 - Production/Stable
Classifier: Environment :: Web Environment
Classifier: Intended Audience :: Developers
Classifier: License :: OSI Approved :: Zero-Clause BSD (0BSD)
Classifier: Operating System :: OS Independent
Classifier: Programming Language :: Python :: 3.9
Classifier: Programming Language :: Python :: 3.10
Classifier: Programming Language :: Python :: 3.11
Classifier: Programming Language :: Python :: 3.12
Classifier: Programming Language :: Python :: 3.13
Classifier: Programming Language :: Python :: 3.14
Classifier: Topic :: Internet :: WWW/HTTP :: Dynamic Content
Classifier: Topic :: Software Development :: Code Generators
Classifier: Topic :: Software Development :: Libraries :: Python Modules
Classifier: Topic :: Text Processing :: Markup :: HTML
Classifier: Typing :: Typed
Requires-Python: >=3.9
Requires-Dist: htmlmin2
Requires-Dist: jinja2
